finalsa/common/models/__init__.py
finalsa/common/models/models/__init__.py
finalsa/common/models/models/functions.py
finalsa/common/models/models/meta.py
finalsa/common/models/models/sqs_response.py
finalsa_common_models-2.0.3.dist-info/METADATA
finalsa_common_models-2.0.3.dist-info/WHEEL
finalsa_common_models-2.0.3.dist-info/licenses/LICENSE.md
finalsa_common_models-2.0.3.dist-info/RECORD
