Metadata-Version: 2.4
Name: finalsa-common-models
Version: 2.0.3
Summary: Common models for Finalsa
Project-URL: Homepage, https://github.com/finalsa/finalsa-common-models
Author-email: Luis Jimenez <luis@finalsa.com>
License: MIT License
License-File: LICENSE.md
Keywords: common,finalsa,models
Requires-Python: >=3.10
Requires-Dist: orjson>=3.10.16
Requires-Dist: pydantic>=2.11.1
Requires-Dist: python-dateutil>=2.9.0.post0
